{
	"template" : "t1",
	"content" : {
		"script":"script.js",
		"data": {
			"title":"Node HTTP2 Server",
			"section1":"This project is a basic http2 web server written in node.js. It can server static files and pages built from template file and json data. Pages can also define files to be pushed to client via http2 push feature. The server can also be modified with custom logic to generate pages.",
			"section2":"",
			"section3":"wtf idk",
			"footer": "<div class='column section'><h4 class='center'>powered By:</h4><image class='quarter' src='images/logo.svg'></div>"
		}
	},
	"push_files": []
}
